aoss_client/__init__.py
aoss_client/client.py
aoss_client/client_base.py
aoss_client/fake_client.py
aoss_client/mixed_client.py
aoss_client/version.py
aoss_client/ceph/__init__.py
aoss_client/ceph/ceph.py
aoss_client/ceph/librgw/__init__.py
aoss_client/ceph/librgw/rados.cpython-36m-x86_64-linux-gnu.so
aoss_client/ceph/librgw/rados.so
aoss_client/ceph/librgw/rgw.cpython-36m-x86_64-linux-gnu.so
aoss_client/ceph/librgw/rgw.so
aoss_client/ceph/librgw/rgw_client.py
aoss_client/ceph/s3/__init__.py
aoss_client/ceph/s3/generator.py
aoss_client/ceph/s3/s3_client.py
aoss_client/ceph/s3cpp/__init__.py
aoss_client/ceph/s3cpp/pys3client.cpython-36m-x86_64-linux-gnu.so
aoss_client/ceph/s3cpp/pys3client.cpython-37m-x86_64-linux-gnu.so
aoss_client/ceph/s3cpp/pys3client.cpython-38-x86_64-linux-gnu.so
aoss_client/ceph/s3cpp/s3_cpp_client.py
aoss_client/ceph/s3cpp/libs/libaws-c-common.so
aoss_client/ceph/s3cpp/libs/libaws-c-event-stream.so
aoss_client/ceph/s3cpp/libs/libaws-checksums.so
aoss_client/ceph/s3cpp/libs/libaws-cpp-sdk-core.so
aoss_client/ceph/s3cpp/libs/libaws-cpp-sdk-s3.so
aoss_client/common/__init__.py
aoss_client/common/config.py
aoss_client/common/exception.py
aoss_client/common/hash.py
aoss_client/common/io_profile.py
aoss_client/common/io_retry.py
aoss_client/common/log.py
aoss_client/common/mem_trace.py
aoss_client/common/uri_parser.py
aoss_client/dfs/__init__.py
aoss_client/dfs/dfs.py
aoss_client/utils/__init__.py
aoss_client/utils/data/__init__.py
aoss_client/utils/data/dataloader.py
aoss_client/utils/data/_utils/__init__.py
aoss_client/utils/data/_utils/pin_memory.py
aoss_client/utils/data/_utils/worker.py
aoss_client/utils/profile/__init__.py
aoss_client/utils/profile/profile.py
fvgtools/__init__.py
fvgtools/mm/__init__.py
fvgtools/mm/data_process.py
fvgtools/utils/__init__.py
fvgtools/utils/ceph_related.py
fvgtools/utils/color.py
fvgtools/utils/decorators.py
fvgtools/utils/load_save.py
fvgtools-0.1.1.dist-info/licenses/LICENSE
fvgtools-0.1.1.dist-info/METADATA
fvgtools-0.1.1.dist-info/WHEEL
fvgtools-0.1.1.dist-info/top_level.txt
fvgtools-0.1.1.dist-info/RECORD
