Metadata-Version: 2.4
Name: fvgtools
Version: 0.1.1
Summary: Data processing tools for Fundamental Vision Group (FVG) of SenseTime Co, Ltd.
Author-email: Jianan Fan <fanjianan@sensetime.com>
License-Expression: MIT
Project-URL: Homepage, https://github.com/SenseTime-FVG
Project-URL: Issues, https://github.com/SenseTime-FVG/uniad_data_process/issues
Classifier: Programming Language :: Python :: 3
Classifier: Operating System :: OS Independent
Requires-Python: >=3.8
License-File: LICENSE
Requires-Dist: Pillow>=10.0.0
Requires-Dist: numpy>=1.19.5
Requires-Dist: boto3
Requires-Dist: requests>=2.20.0
Requires-Dist: coloredlogs
Requires-Dist: environs
Requires-Dist: humanize
Requires-Dist: multiprocessing-logging
Dynamic: license-file
